{"agent_count":2,"goals_per_agent":2,"tsp-branch-and-bound-cbs":380,"tsp-branch-and-bound-initial":380,"tsp-exact-cbs":380,"tsp-exact-initial":380,"tsp-nn-cbs":380,"tsp-nn-initial":380}
{"agent_count":2,"goals_per_agent":2,"tsp-branch-and-bound-cbs":348,"tsp-branch-and-bound-initial":348,"tsp-exact-cbs":348,"tsp-exact-initial":348,"tsp-nn-cbs":348,"tsp-nn-initial":348}
{"agent_count":2,"goals_per_agent":3,"tsp-branch-and-bound-cbs":642,"tsp-branch-and-bound-initial":642,"tsp-exact-cbs":642,"tsp-exact-initial":642,"tsp-nn-cbs":644,"tsp-nn-initial":644}
{"agent_count":2,"goals_per_agent":3,"tsp-branch-and-bound-cbs":382,"tsp-branch-and-bound-initial":382,"tsp-exact-cbs":382,"tsp-exact-initial":382,"tsp-nn-cbs":382,"tsp-nn-initial":382}
{"agent_count":2,"goals_per_agent":4,"tsp-branch-and-bound-cbs":686,"tsp-branch-and-bound-initial":686,"tsp-exact-cbs":686,"tsp-exact-initial":686,"tsp-nn-cbs":714,"tsp-nn-initial":714}
{"agent_count":2,"goals_per_agent":4,"tsp-branch-and-bound-cbs":826,"tsp-branch-and-bound-initial":826,"tsp-exact-cbs":826,"tsp-exact-initial":826,"tsp-nn-cbs":840,"tsp-nn-initial":840}
{"agent_count":2,"goals_per_agent":5,"tsp-branch-and-bound-cbs":692,"tsp-branch-and-bound-initial":692,"tsp-exact-cbs":692,"tsp-exact-initial":692,"tsp-nn-cbs":702,"tsp-nn-initial":702}
{"agent_count":2,"goals_per_agent":6,"tsp-branch-and-bound-cbs":668,"tsp-branch-and-bound-initial":668,"tsp-exact-cbs":668,"tsp-exact-initial":668,"tsp-nn-cbs":766,"tsp-nn-initial":764}
{"agent_count":2,"goals_per_agent":6,"tsp-branch-and-bound-cbs":782,"tsp-branch-and-bound-initial":782,"tsp-exact-cbs":782,"tsp-exact-initial":782,"tsp-nn-cbs":822,"tsp-nn-initial":822}
{"agent_count":2,"goals_per_agent":7,"tsp-branch-and-bound-cbs":772,"tsp-branch-and-bound-initial":772,"tsp-exact-cbs":772,"tsp-exact-initial":772,"tsp-nn-cbs":842,"tsp-nn-initial":842}
{"agent_count":2,"goals_per_agent":7,"tsp-branch-and-bound-cbs":766,"tsp-branch-and-bound-initial":766,"tsp-exact-cbs":766,"tsp-exact-initial":766,"tsp-nn-cbs":784,"tsp-nn-initial":784}
{"agent_count":2,"goals_per_agent":8,"tsp-branch-and-bound-cbs":820,"tsp-branch-and-bound-initial":820,"tsp-exact-cbs":820,"tsp-exact-initial":820,"tsp-nn-cbs":918,"tsp-nn-initial":918}
{"agent_count":2,"goals_per_agent":8,"tsp-branch-and-bound-cbs":818,"tsp-branch-and-bound-initial":818,"tsp-exact-cbs":818,"tsp-exact-initial":818,"tsp-nn-cbs":852,"tsp-nn-initial":852}
{"agent_count":2,"goals_per_agent":9,"tsp-branch-and-bound-cbs":782,"tsp-branch-and-bound-initial":782,"tsp-exact-cbs":782,"tsp-exact-initial":782,"tsp-nn-cbs":942,"tsp-nn-initial":942}
{"agent_count":2,"goals_per_agent":9,"tsp-branch-and-bound-cbs":818,"tsp-branch-and-bound-initial":818,"tsp-exact-cbs":818,"tsp-exact-initial":818,"tsp-nn-cbs":888,"tsp-nn-initial":888}
{"agent_count":2,"goals_per_agent":10,"tsp-branch-and-bound-cbs":760,"tsp-branch-and-bound-initial":760,"tsp-exact-cbs":-99,"tsp-exact-initial":-99,"tsp-nn-cbs":866,"tsp-nn-initial":866}
{"agent_count":2,"goals_per_agent":10,"tsp-branch-and-bound-cbs":814,"tsp-branch-and-bound-initial":814,"tsp-exact-cbs":-99,"tsp-exact-initial":-99,"tsp-nn-cbs":958,"tsp-nn-initial":948}
{"agent_count":3,"goals_per_agent":2,"tsp-branch-and-bound-cbs":806,"tsp-branch-and-bound-initial":806,"tsp-exact-cbs":806,"tsp-exact-initial":806,"tsp-nn-cbs":806,"tsp-nn-initial":806}
{"agent_count":3,"goals_per_agent":2,"tsp-branch-and-bound-cbs":964,"tsp-branch-and-bound-initial":964,"tsp-exact-cbs":964,"tsp-exact-initial":964,"tsp-nn-cbs":964,"tsp-nn-initial":964}
{"agent_count":3,"goals_per_agent":3,"tsp-branch-and-bound-cbs":936,"tsp-branch-and-bound-initial":936,"tsp-exact-cbs":936,"tsp-exact-initial":936,"tsp-nn-cbs":936,"tsp-nn-initial":936}
{"agent_count":3,"goals_per_agent":3,"tsp-branch-and-bound-cbs":680,"tsp-branch-and-bound-initial":680,"tsp-exact-cbs":680,"tsp-exact-initial":680,"tsp-nn-cbs":720,"tsp-nn-initial":720}
{"agent_count":3,"goals_per_agent":4,"tsp-branch-and-bound-cbs":942,"tsp-branch-and-bound-initial":942,"tsp-exact-cbs":942,"tsp-exact-initial":942,"tsp-nn-cbs":1036,"tsp-nn-initial":1036}
{"agent_count":3,"goals_per_agent":4,"tsp-branch-and-bound-cbs":1012,"tsp-branch-and-bound-initial":1012,"tsp-exact-cbs":1012,"tsp-exact-initial":1012,"tsp-nn-cbs":1040,"tsp-nn-initial":1040}
{"agent_count":3,"goals_per_agent":5,"tsp-branch-and-bound-cbs":1088,"tsp-branch-and-bound-initial":1088,"tsp-exact-cbs":1088,"tsp-exact-initial":1088,"tsp-nn-cbs":1222,"tsp-nn-initial":1222}
{"agent_count":3,"goals_per_agent":5,"tsp-branch-and-bound-cbs":980,"tsp-branch-and-bound-initial":980,"tsp-exact-cbs":980,"tsp-exact-initial":980,"tsp-nn-cbs":998,"tsp-nn-initial":998}
{"agent_count":3,"goals_per_agent":6,"tsp-branch-and-bound-cbs":1016,"tsp-branch-and-bound-initial":1016,"tsp-exact-cbs":1022,"tsp-exact-initial":1016,"tsp-nn-cbs":1124,"tsp-nn-initial":1124}
{"agent_count":3,"goals_per_agent":6,"tsp-branch-and-bound-cbs":1072,"tsp-branch-and-bound-initial":1072,"tsp-exact-cbs":1072,"tsp-exact-initial":1072,"tsp-nn-cbs":1114,"tsp-nn-initial":1114}
{"agent_count":3,"goals_per_agent":7,"tsp-branch-and-bound-cbs":1148,"tsp-branch-and-bound-initial":1148,"tsp-exact-cbs":1148,"tsp-exact-initial":1148,"tsp-nn-cbs":1284,"tsp-nn-initial":1284}
{"agent_count":3,"goals_per_agent":7,"tsp-branch-and-bound-cbs":1198,"tsp-branch-and-bound-initial":1198,"tsp-exact-cbs":1198,"tsp-exact-initial":1198,"tsp-nn-cbs":1364,"tsp-nn-initial":1364}
{"agent_count":3,"goals_per_agent":8,"tsp-branch-and-bound-cbs":1266,"tsp-branch-and-bound-initial":1266,"tsp-exact-cbs":1266,"tsp-exact-initial":1266,"tsp-nn-cbs":1388,"tsp-nn-initial":1388}
{"agent_count":3,"goals_per_agent":8,"tsp-branch-and-bound-cbs":1132,"tsp-branch-and-bound-initial":1132,"tsp-exact-cbs":1132,"tsp-exact-initial":1132,"tsp-nn-cbs":1214,"tsp-nn-initial":1214}
{"agent_count":3,"goals_per_agent":9,"tsp-branch-and-bound-cbs":1014,"tsp-branch-and-bound-initial":1014,"tsp-exact-cbs":1014,"tsp-exact-initial":1014,"tsp-nn-cbs":1100,"tsp-nn-initial":1100}
{"agent_count":3,"goals_per_agent":9,"tsp-branch-and-bound-cbs":1238,"tsp-branch-and-bound-initial":1238,"tsp-exact-cbs":1238,"tsp-exact-initial":1238,"tsp-nn-cbs":1302,"tsp-nn-initial":1302}
{"agent_count":3,"goals_per_agent":10,"tsp-branch-and-bound-cbs":1270,"tsp-branch-and-bound-initial":1270,"tsp-exact-cbs":-99,"tsp-exact-initial":-99,"tsp-nn-cbs":1470,"tsp-nn-initial":1470}
{"agent_count":4,"goals_per_agent":2,"tsp-branch-and-bound-cbs":1106,"tsp-branch-and-bound-initial":1106,"tsp-exact-cbs":1106,"tsp-exact-initial":1106,"tsp-nn-cbs":1106,"tsp-nn-initial":1106}
{"agent_count":4,"goals_per_agent":2,"tsp-branch-and-bound-cbs":988,"tsp-branch-and-bound-initial":988,"tsp-exact-cbs":988,"tsp-exact-initial":988,"tsp-nn-cbs":988,"tsp-nn-initial":988}
{"agent_count":4,"goals_per_agent":3,"tsp-branch-and-bound-cbs":1024,"tsp-branch-and-bound-initial":1024,"tsp-exact-cbs":1024,"tsp-exact-initial":1024,"tsp-nn-cbs":1080,"tsp-nn-initial":1080}
{"agent_count":4,"goals_per_agent":3,"tsp-branch-and-bound-cbs":1134,"tsp-branch-and-bound-initial":1134,"tsp-exact-cbs":1134,"tsp-exact-initial":1134,"tsp-nn-cbs":1166,"tsp-nn-initial":1160}
{"agent_count":4,"goals_per_agent":4,"tsp-branch-and-bound-cbs":1290,"tsp-branch-and-bound-initial":1290,"tsp-exact-cbs":1290,"tsp-exact-initial":1290,"tsp-nn-cbs":1306,"tsp-nn-initial":1306}
{"agent_count":4,"goals_per_agent":4,"tsp-branch-and-bound-cbs":1498,"tsp-branch-and-bound-initial":1498,"tsp-exact-cbs":1498,"tsp-exact-initial":1498,"tsp-nn-cbs":1498,"tsp-nn-initial":1498}
{"agent_count":4,"goals_per_agent":5,"tsp-branch-and-bound-cbs":1362,"tsp-branch-and-bound-initial":1362,"tsp-exact-cbs":1362,"tsp-exact-initial":1362,"tsp-nn-cbs":1422,"tsp-nn-initial":1422}
{"agent_count":4,"goals_per_agent":5,"tsp-branch-and-bound-cbs":1390,"tsp-branch-and-bound-initial":1390,"tsp-exact-cbs":1390,"tsp-exact-initial":1390,"tsp-nn-cbs":1420,"tsp-nn-initial":1420}
{"agent_count":4,"goals_per_agent":6,"tsp-branch-and-bound-cbs":1540,"tsp-branch-and-bound-initial":1540,"tsp-exact-cbs":1540,"tsp-exact-initial":1540,"tsp-nn-cbs":1616,"tsp-nn-initial":1616}
{"agent_count":4,"goals_per_agent":6,"tsp-branch-and-bound-cbs":1650,"tsp-branch-and-bound-initial":1650,"tsp-exact-cbs":1650,"tsp-exact-initial":1650,"tsp-nn-cbs":1706,"tsp-nn-initial":1706}
{"agent_count":4,"goals_per_agent":7,"tsp-branch-and-bound-cbs":1590,"tsp-branch-and-bound-initial":1590,"tsp-exact-cbs":1590,"tsp-exact-initial":1590,"tsp-nn-cbs":1740,"tsp-nn-initial":1740}
{"agent_count":4,"goals_per_agent":7,"tsp-branch-and-bound-cbs":1544,"tsp-branch-and-bound-initial":1544,"tsp-exact-cbs":1544,"tsp-exact-initial":1544,"tsp-nn-cbs":1640,"tsp-nn-initial":1640}
{"agent_count":4,"goals_per_agent":8,"tsp-branch-and-bound-cbs":1666,"tsp-branch-and-bound-initial":1666,"tsp-exact-cbs":1666,"tsp-exact-initial":1666,"tsp-nn-cbs":1818,"tsp-nn-initial":1818}
{"agent_count":4,"goals_per_agent":8,"tsp-branch-and-bound-cbs":1500,"tsp-branch-and-bound-initial":1500,"tsp-exact-cbs":1500,"tsp-exact-initial":1500,"tsp-nn-cbs":1666,"tsp-nn-initial":1666}
{"agent_count":4,"goals_per_agent":9,"tsp-branch-and-bound-cbs":1636,"tsp-branch-and-bound-initial":1636,"tsp-exact-cbs":1636,"tsp-exact-initial":1636,"tsp-nn-cbs":1958,"tsp-nn-initial":1958}
{"agent_count":4,"goals_per_agent":9,"tsp-branch-and-bound-cbs":1532,"tsp-branch-and-bound-initial":1532,"tsp-exact-cbs":1532,"tsp-exact-initial":1532,"tsp-nn-cbs":1846,"tsp-nn-initial":1846}
{"agent_count":4,"goals_per_agent":10,"tsp-branch-and-bound-cbs":1728,"tsp-branch-and-bound-initial":1728,"tsp-exact-cbs":-99,"tsp-exact-initial":-99,"tsp-nn-cbs":1928,"tsp-nn-initial":1928}
{"agent_count":5,"goals_per_agent":2,"tsp-branch-and-bound-cbs":1464,"tsp-branch-and-bound-initial":1464,"tsp-exact-cbs":1464,"tsp-exact-initial":1464,"tsp-nn-cbs":1464,"tsp-nn-initial":1464}
{"agent_count":5,"goals_per_agent":2,"tsp-branch-and-bound-cbs":1730,"tsp-branch-and-bound-initial":1730,"tsp-exact-cbs":1730,"tsp-exact-initial":1730,"tsp-nn-cbs":1730,"tsp-nn-initial":1730}
{"agent_count":5,"goals_per_agent":3,"tsp-branch-and-bound-cbs":1238,"tsp-branch-and-bound-initial":1238,"tsp-exact-cbs":1238,"tsp-exact-initial":1238,"tsp-nn-cbs":1246,"tsp-nn-initial":1246}
{"agent_count":5,"goals_per_agent":3,"tsp-branch-and-bound-cbs":1270,"tsp-branch-and-bound-initial":1270,"tsp-exact-cbs":1270,"tsp-exact-initial":1270,"tsp-nn-cbs":1270,"tsp-nn-initial":1270}
{"agent_count":5,"goals_per_agent":4,"tsp-branch-and-bound-cbs":1688,"tsp-branch-and-bound-initial":1688,"tsp-exact-cbs":1688,"tsp-exact-initial":1688,"tsp-nn-cbs":1740,"tsp-nn-initial":1740}
{"agent_count":5,"goals_per_agent":4,"tsp-branch-and-bound-cbs":1750,"tsp-branch-and-bound-initial":1750,"tsp-exact-cbs":1750,"tsp-exact-initial":1750,"tsp-nn-cbs":1790,"tsp-nn-initial":1790}
{"agent_count":5,"goals_per_agent":5,"tsp-branch-and-bound-cbs":1582,"tsp-branch-and-bound-initial":1582,"tsp-exact-cbs":1582,"tsp-exact-initial":1582,"tsp-nn-cbs":1698,"tsp-nn-initial":1698}
{"agent_count":5,"goals_per_agent":5,"tsp-branch-and-bound-cbs":1686,"tsp-branch-and-bound-initial":1686,"tsp-exact-cbs":1686,"tsp-exact-initial":1686,"tsp-nn-cbs":1758,"tsp-nn-initial":1758}
{"agent_count":5,"goals_per_agent":6,"tsp-branch-and-bound-cbs":1864,"tsp-branch-and-bound-initial":1864,"tsp-exact-cbs":1864,"tsp-exact-initial":1864,"tsp-nn-cbs":2030,"tsp-nn-initial":2030}
{"agent_count":5,"goals_per_agent":6,"tsp-branch-and-bound-cbs":1882,"tsp-branch-and-bound-initial":1878,"tsp-exact-cbs":1878,"tsp-exact-initial":1878,"tsp-nn-cbs":2014,"tsp-nn-initial":2008}
{"agent_count":5,"goals_per_agent":7,"tsp-branch-and-bound-cbs":1848,"tsp-branch-and-bound-initial":1848,"tsp-exact-cbs":1848,"tsp-exact-initial":1848,"tsp-nn-cbs":2074,"tsp-nn-initial":2074}
{"agent_count":5,"goals_per_agent":7,"tsp-branch-and-bound-cbs":1852,"tsp-branch-and-bound-initial":1852,"tsp-exact-cbs":1852,"tsp-exact-initial":1852,"tsp-nn-cbs":2034,"tsp-nn-initial":2034}
{"agent_count":5,"goals_per_agent":9,"tsp-branch-and-bound-cbs":2062,"tsp-branch-and-bound-initial":2062,"tsp-exact-cbs":2062,"tsp-exact-initial":2062,"tsp-nn-cbs":2416,"tsp-nn-initial":2416}
{"agent_count":5,"goals_per_agent":9,"tsp-branch-and-bound-cbs":2110,"tsp-branch-and-bound-initial":2110,"tsp-exact-cbs":2110,"tsp-exact-initial":2110,"tsp-nn-cbs":2338,"tsp-nn-initial":2338}
{"agent_count":6,"goals_per_agent":2,"tsp-branch-and-bound-cbs":1688,"tsp-branch-and-bound-initial":1688,"tsp-exact-cbs":1688,"tsp-exact-initial":1688,"tsp-nn-cbs":1688,"tsp-nn-initial":1688}
{"agent_count":6,"goals_per_agent":2,"tsp-branch-and-bound-cbs":1312,"tsp-branch-and-bound-initial":1312,"tsp-exact-cbs":1312,"tsp-exact-initial":1312,"tsp-nn-cbs":1312,"tsp-nn-initial":1312}
{"agent_count":6,"goals_per_agent":3,"tsp-branch-and-bound-cbs":1746,"tsp-branch-and-bound-initial":1746,"tsp-exact-cbs":1746,"tsp-exact-initial":1746,"tsp-nn-cbs":1772,"tsp-nn-initial":1772}
{"agent_count":6,"goals_per_agent":3,"tsp-branch-and-bound-cbs":1610,"tsp-branch-and-bound-initial":1610,"tsp-exact-cbs":1610,"tsp-exact-initial":1610,"tsp-nn-cbs":1612,"tsp-nn-initial":1612}
{"agent_count":6,"goals_per_agent":4,"tsp-branch-and-bound-cbs":2182,"tsp-branch-and-bound-initial":2182,"tsp-exact-cbs":2182,"tsp-exact-initial":2182,"tsp-nn-cbs":2412,"tsp-nn-initial":2412}
{"agent_count":6,"goals_per_agent":4,"tsp-branch-and-bound-cbs":1616,"tsp-branch-and-bound-initial":1616,"tsp-exact-cbs":1616,"tsp-exact-initial":1616,"tsp-nn-cbs":1686,"tsp-nn-initial":1686}
{"agent_count":6,"goals_per_agent":5,"tsp-branch-and-bound-cbs":2174,"tsp-branch-and-bound-initial":2174,"tsp-exact-cbs":2174,"tsp-exact-initial":2174,"tsp-nn-cbs":2320,"tsp-nn-initial":2320}
{"agent_count":6,"goals_per_agent":5,"tsp-branch-and-bound-cbs":2040,"tsp-branch-and-bound-initial":2040,"tsp-exact-cbs":2040,"tsp-exact-initial":2040,"tsp-nn-cbs":2132,"tsp-nn-initial":2132}
{"agent_count":6,"goals_per_agent":6,"tsp-branch-and-bound-cbs":2270,"tsp-branch-and-bound-initial":2270,"tsp-exact-cbs":2270,"tsp-exact-initial":2270,"tsp-nn-cbs":2582,"tsp-nn-initial":2582}
{"agent_count":6,"goals_per_agent":7,"tsp-branch-and-bound-cbs":2246,"tsp-branch-and-bound-initial":2246,"tsp-exact-cbs":2248,"tsp-exact-initial":2246,"tsp-nn-cbs":2532,"tsp-nn-initial":2532}
{"agent_count":6,"goals_per_agent":7,"tsp-branch-and-bound-cbs":2156,"tsp-branch-and-bound-initial":2156,"tsp-exact-cbs":2156,"tsp-exact-initial":2156,"tsp-nn-cbs":2374,"tsp-nn-initial":2374}
{"agent_count":6,"goals_per_agent":8,"tsp-branch-and-bound-cbs":2256,"tsp-branch-and-bound-initial":2256,"tsp-exact-cbs":2256,"tsp-exact-initial":2256,"tsp-nn-cbs":2424,"tsp-nn-initial":2424}
{"agent_count":6,"goals_per_agent":8,"tsp-branch-and-bound-cbs":2308,"tsp-branch-and-bound-initial":2308,"tsp-exact-cbs":2308,"tsp-exact-initial":2308,"tsp-nn-cbs":2642,"tsp-nn-initial":2642}
{"agent_count":6,"goals_per_agent":9,"tsp-branch-and-bound-cbs":2430,"tsp-branch-and-bound-initial":2426,"tsp-exact-cbs":2426,"tsp-exact-initial":2426,"tsp-nn-cbs":2732,"tsp-nn-initial":2732}
{"agent_count":7,"goals_per_agent":2,"tsp-branch-and-bound-cbs":1950,"tsp-branch-and-bound-initial":1950,"tsp-exact-cbs":1950,"tsp-exact-initial":1950,"tsp-nn-cbs":1950,"tsp-nn-initial":1950}
{"agent_count":7,"goals_per_agent":2,"tsp-branch-and-bound-cbs":1830,"tsp-branch-and-bound-initial":1830,"tsp-exact-cbs":1830,"tsp-exact-initial":1830,"tsp-nn-cbs":1830,"tsp-nn-initial":1830}
{"agent_count":7,"goals_per_agent":3,"tsp-branch-and-bound-cbs":2114,"tsp-branch-and-bound-initial":2114,"tsp-exact-cbs":2114,"tsp-exact-initial":2114,"tsp-nn-cbs":2194,"tsp-nn-initial":2194}
{"agent_count":7,"goals_per_agent":3,"tsp-branch-and-bound-cbs":1968,"tsp-branch-and-bound-initial":1968,"tsp-exact-cbs":1968,"tsp-exact-initial":1968,"tsp-nn-cbs":1988,"tsp-nn-initial":1988}
{"agent_count":7,"goals_per_agent":4,"tsp-branch-and-bound-cbs":2534,"tsp-branch-and-bound-initial":2534,"tsp-exact-cbs":2534,"tsp-exact-initial":2534,"tsp-nn-cbs":2572,"tsp-nn-initial":2572}
{"agent_count":7,"goals_per_agent":4,"tsp-branch-and-bound-cbs":1994,"tsp-branch-and-bound-initial":1994,"tsp-exact-cbs":1994,"tsp-exact-initial":1994,"tsp-nn-cbs":2076,"tsp-nn-initial":2076}
{"agent_count":7,"goals_per_agent":5,"tsp-branch-and-bound-cbs":2288,"tsp-branch-and-bound-initial":2288,"tsp-exact-cbs":2290,"tsp-exact-initial":2288,"tsp-nn-cbs":2354,"tsp-nn-initial":2354}
{"agent_count":7,"goals_per_agent":5,"tsp-branch-and-bound-cbs":2284,"tsp-branch-and-bound-initial":2284,"tsp-exact-cbs":2284,"tsp-exact-initial":2284,"tsp-nn-cbs":2392,"tsp-nn-initial":2392}
{"agent_count":7,"goals_per_agent":6,"tsp-branch-and-bound-cbs":2488,"tsp-branch-and-bound-initial":2488,"tsp-exact-cbs":2488,"tsp-exact-initial":2488,"tsp-nn-cbs":2736,"tsp-nn-initial":2736}
{"agent_count":7,"goals_per_agent":7,"tsp-branch-and-bound-cbs":2394,"tsp-branch-and-bound-initial":2394,"tsp-exact-cbs":2394,"tsp-exact-initial":2394,"tsp-nn-cbs":2630,"tsp-nn-initial":2630}
{"agent_count":7,"goals_per_agent":7,"tsp-branch-and-bound-cbs":2574,"tsp-branch-and-bound-initial":2574,"tsp-exact-cbs":2574,"tsp-exact-initial":2574,"tsp-nn-cbs":2714,"tsp-nn-initial":2714}
{"agent_count":7,"goals_per_agent":8,"tsp-branch-and-bound-cbs":2568,"tsp-branch-and-bound-initial":2568,"tsp-exact-cbs":2564,"tsp-exact-initial":2564,"tsp-nn-cbs":2796,"tsp-nn-initial":2796}
{"agent_count":7,"goals_per_agent":9,"tsp-branch-and-bound-cbs":2844,"tsp-branch-and-bound-initial":2844,"tsp-exact-cbs":2844,"tsp-exact-initial":2844,"tsp-nn-cbs":3350,"tsp-nn-initial":3350}
{"agent_count":8,"goals_per_agent":2,"tsp-branch-and-bound-cbs":1508,"tsp-branch-and-bound-initial":1508,"tsp-exact-cbs":1508,"tsp-exact-initial":1508,"tsp-nn-cbs":1508,"tsp-nn-initial":1508}
{"agent_count":8,"goals_per_agent":2,"tsp-branch-and-bound-cbs":1902,"tsp-branch-and-bound-initial":1902,"tsp-exact-cbs":1902,"tsp-exact-initial":1902,"tsp-nn-cbs":1902,"tsp-nn-initial":1902}
{"agent_count":8,"goals_per_agent":3,"tsp-branch-and-bound-cbs":1884,"tsp-branch-and-bound-initial":1884,"tsp-exact-cbs":1884,"tsp-exact-initial":1884,"tsp-nn-cbs":1950,"tsp-nn-initial":1950}
{"agent_count":8,"goals_per_agent":3,"tsp-branch-and-bound-cbs":2388,"tsp-branch-and-bound-initial":2388,"tsp-exact-cbs":2388,"tsp-exact-initial":2388,"tsp-nn-cbs":2408,"tsp-nn-initial":2408}
{"agent_count":8,"goals_per_agent":4,"tsp-branch-and-bound-cbs":2982,"tsp-branch-and-bound-initial":2982,"tsp-exact-cbs":2982,"tsp-exact-initial":2982,"tsp-nn-cbs":3196,"tsp-nn-initial":3196}
{"agent_count":8,"goals_per_agent":4,"tsp-branch-and-bound-cbs":2864,"tsp-branch-and-bound-initial":2864,"tsp-exact-cbs":2864,"tsp-exact-initial":2864,"tsp-nn-cbs":2940,"tsp-nn-initial":2940}
{"agent_count":8,"goals_per_agent":5,"tsp-branch-and-bound-cbs":2662,"tsp-branch-and-bound-initial":2662,"tsp-exact-cbs":2662,"tsp-exact-initial":2662,"tsp-nn-cbs":2744,"tsp-nn-initial":2744}
{"agent_count":8,"goals_per_agent":5,"tsp-branch-and-bound-cbs":2864,"tsp-branch-and-bound-initial":2862,"tsp-exact-cbs":2862,"tsp-exact-initial":2862,"tsp-nn-cbs":2940,"tsp-nn-initial":2938}
{"agent_count":8,"goals_per_agent":6,"tsp-branch-and-bound-cbs":2986,"tsp-branch-and-bound-initial":2986,"tsp-exact-cbs":2986,"tsp-exact-initial":2986,"tsp-nn-cbs":3136,"tsp-nn-initial":3134}
{"agent_count":8,"goals_per_agent":6,"tsp-branch-and-bound-cbs":2830,"tsp-branch-and-bound-initial":2830,"tsp-exact-cbs":2830,"tsp-exact-initial":2830,"tsp-nn-cbs":3038,"tsp-nn-initial":3038}
{"agent_count":8,"goals_per_agent":7,"tsp-branch-and-bound-cbs":3042,"tsp-branch-and-bound-initial":3042,"tsp-exact-cbs":3042,"tsp-exact-initial":3042,"tsp-nn-cbs":3336,"tsp-nn-initial":3336}
{"agent_count":8,"goals_per_agent":8,"tsp-branch-and-bound-cbs":3102,"tsp-branch-and-bound-initial":3102,"tsp-exact-cbs":3102,"tsp-exact-initial":3102,"tsp-nn-cbs":3226,"tsp-nn-initial":3226}
{"agent_count":8,"goals_per_agent":10,"tsp-branch-and-bound-cbs":3396,"tsp-branch-and-bound-initial":3390,"tsp-exact-cbs":-99,"tsp-exact-initial":-99,"tsp-nn-cbs":3790,"tsp-nn-initial":3790}
{"agent_count":9,"goals_per_agent":2,"tsp-branch-and-bound-cbs":2364,"tsp-branch-and-bound-initial":2364,"tsp-exact-cbs":2364,"tsp-exact-initial":2364,"tsp-nn-cbs":2364,"tsp-nn-initial":2364}
{"agent_count":9,"goals_per_agent":3,"tsp-branch-and-bound-cbs":2782,"tsp-branch-and-bound-initial":2782,"tsp-exact-cbs":2782,"tsp-exact-initial":2782,"tsp-nn-cbs":2818,"tsp-nn-initial":2818}
{"agent_count":9,"goals_per_agent":3,"tsp-branch-and-bound-cbs":2342,"tsp-branch-and-bound-initial":2342,"tsp-exact-cbs":2342,"tsp-exact-initial":2342,"tsp-nn-cbs":2422,"tsp-nn-initial":2422}
{"agent_count":9,"goals_per_agent":4,"tsp-branch-and-bound-cbs":2860,"tsp-branch-and-bound-initial":2860,"tsp-exact-cbs":2860,"tsp-exact-initial":2860,"tsp-nn-cbs":3068,"tsp-nn-initial":3068}
{"agent_count":9,"goals_per_agent":4,"tsp-branch-and-bound-cbs":3082,"tsp-branch-and-bound-initial":3082,"tsp-exact-cbs":3082,"tsp-exact-initial":3082,"tsp-nn-cbs":3134,"tsp-nn-initial":3134}
{"agent_count":9,"goals_per_agent":5,"tsp-branch-and-bound-cbs":3412,"tsp-branch-and-bound-initial":3412,"tsp-exact-cbs":3412,"tsp-exact-initial":3412,"tsp-nn-cbs":3690,"tsp-nn-initial":3690}
{"agent_count":9,"goals_per_agent":6,"tsp-branch-and-bound-cbs":3442,"tsp-branch-and-bound-initial":3442,"tsp-exact-cbs":3442,"tsp-exact-initial":3442,"tsp-nn-cbs":3804,"tsp-nn-initial":3804}
{"agent_count":9,"goals_per_agent":6,"tsp-branch-and-bound-cbs":3200,"tsp-branch-and-bound-initial":3200,"tsp-exact-cbs":3200,"tsp-exact-initial":3200,"tsp-nn-cbs":3460,"tsp-nn-initial":3450}
{"agent_count":9,"goals_per_agent":7,"tsp-branch-and-bound-cbs":3462,"tsp-branch-and-bound-initial":3462,"tsp-exact-cbs":3462,"tsp-exact-initial":3462,"tsp-nn-cbs":3560,"tsp-nn-initial":3558}
{"agent_count":9,"goals_per_agent":10,"tsp-branch-and-bound-cbs":3340,"tsp-branch-and-bound-initial":3340,"tsp-exact-cbs":-99,"tsp-exact-initial":-99,"tsp-nn-cbs":3978,"tsp-nn-initial":3978}
{"agent_count":10,"goals_per_agent":4,"tsp-branch-and-bound-cbs":3410,"tsp-branch-and-bound-initial":3410,"tsp-exact-cbs":3410,"tsp-exact-initial":3410,"tsp-nn-cbs":3530,"tsp-nn-initial":3530}
{"agent_count":10,"goals_per_agent":4,"tsp-branch-and-bound-cbs":3448,"tsp-branch-and-bound-initial":3448,"tsp-exact-cbs":3448,"tsp-exact-initial":3448,"tsp-nn-cbs":3518,"tsp-nn-initial":3518}
{"agent_count":10,"goals_per_agent":5,"tsp-branch-and-bound-cbs":3438,"tsp-branch-and-bound-initial":3438,"tsp-exact-cbs":3438,"tsp-exact-initial":3438,"tsp-nn-cbs":3616,"tsp-nn-initial":3616}
{"agent_count":10,"goals_per_agent":5,"tsp-branch-and-bound-cbs":3476,"tsp-branch-and-bound-initial":3476,"tsp-exact-cbs":3476,"tsp-exact-initial":3476,"tsp-nn-cbs":3598,"tsp-nn-initial":3598}
{"agent_count":10,"goals_per_agent":6,"tsp-branch-and-bound-cbs":3690,"tsp-branch-and-bound-initial":3690,"tsp-exact-cbs":3690,"tsp-exact-initial":3690,"tsp-nn-cbs":3902,"tsp-nn-initial":3902}
{"agent_count":10,"goals_per_agent":2,"tsp-branch-and-bound-cbs":2282,"tsp-branch-and-bound-initial":2276,"tsp-exact-cbs":2282,"tsp-exact-initial":2276,"tsp-nn-cbs":2276,"tsp-nn-initial":2276}
{"agent_count":10,"goals_per_agent":2,"tsp-branch-and-bound-cbs":2510,"tsp-branch-and-bound-initial":2510,"tsp-exact-cbs":2510,"tsp-exact-initial":2510,"tsp-nn-cbs":2510,"tsp-nn-initial":2510}
{"agent_count":10,"goals_per_agent":3,"tsp-branch-and-bound-cbs":2732,"tsp-branch-and-bound-initial":2732,"tsp-exact-cbs":2732,"tsp-exact-initial":2732,"tsp-nn-cbs":2756,"tsp-nn-initial":2756}
{"agent_count":10,"goals_per_agent":3,"tsp-branch-and-bound-cbs":2896,"tsp-branch-and-bound-initial":2896,"tsp-exact-cbs":2896,"tsp-exact-initial":2896,"tsp-nn-cbs":2916,"tsp-nn-initial":2916}